cas_gui_2/__init__.py
cas_gui_2/database.py
cas_gui_2/deneme.py
cas_gui_2/functions.py
cas_gui_2/indicator_dark_rc.py
cas_gui_2/indicator_rc.py
cas_gui_2/interface.py
cas_gui_2/main.py
cas_gui_2/missions_enum.py
cas_gui_2/qfi_ADI.py
cas_gui_2/qfi_ADI_dark.py
cas_gui_2/source_rc.py
cas_gui_2/style.py
casmarinedeneme2-0.0.5.dist-info/METADATA
casmarinedeneme2-0.0.5.dist-info/WHEEL
casmarinedeneme2-0.0.5.dist-info/top_level.txt
casmarinedeneme2-0.0.5.dist-info/RECORD
