Metadata-Version: 2.1
Name: casmarinedeneme2
Version: 0.0.5
Summary: CasMarine
Home-page: UNKNOWN
Author: mubarizmuradov
Author-email: UNKNOWN
License: UNKNOWN
Platform: UNKNOWN
Classifier: Development Status :: 1 - Planning
Classifier: Intended Audience :: Developers
Classifier: Programming Language :: Python :: 3
Classifier: Operating System :: Unix
Classifier: Operating System :: MacOS :: MacOS X
Classifier: Operating System :: Microsoft :: Windows
Requires-Dist: PyQt5
Requires-Dist: future
Requires-Dist: numpy
Requires-Dist: opencv-python
Requires-Dist: python-math
Requires-Dist: wheel
